proteomics_converter/adat_func.py
proteomics_converter/adat_reader.py
proteomics_converter/create_database.py
proteomics_converter/create_tables.py
proteomics_converter/pandora_func.py
proteomics_converter/read_tables.py
proteomics_converter-1.0.1.dist-info/METADATA
proteomics_converter-1.0.1.dist-info/WHEEL
proteomics_converter-1.0.1.dist-info/RECORD
