Metadata-Version: 2.1
Name: proteomics-converter
Version: 1.0.1
Summary: 
Author: the
Author-email: the@illumina.com
Requires-Python: >=3.9,<4.0
Classifier: Programming Language :: Python :: 3
Classifier: Programming Language :: Python :: 3.9
Classifier: Programming Language :: Python :: 3.10
Classifier: Programming Language :: Python :: 3.11
Classifier: Programming Language :: Python :: 3.12
Requires-Dist: pyyaml (>=6.0.2,<7.0.0)
Requires-Dist: somadata (>=1.0.0,<2.0.0)
